<annotation>
	<folder>training2</folder>
	<filename>2b2cb716-864e-11eb-9e4d-005056c00008.png</filename>
	<path>C:\MyD\Python\tensorflow2\captcha\my_custom_detection\images\train\2b2cb716-864e-11eb-9e4d-005056c00008.png</path>
	<source>
		<database>Unknown</database>
	</source>
	<size>
		<width>215</width>
		<height>79</height>
		<depth>3</depth>
	</size>
	<segmented>0</segmented>
	<object>
		<name>2</name>
		<pose>Unspecified</pose>
		<truncated>0</truncated>
		<difficult>0</difficult>
		<bndbox>
			<xmin>4</xmin>
			<ymin>15</ymin>
			<xmax>39</xmax>
			<ymax>67</ymax>
		</bndbox>
	</object>
	<object>
		<name>b</name>
		<pose>Unspecified</pose>
		<truncated>0</truncated>
		<difficult>0</difficult>
		<bndbox>
			<xmin>42</xmin>
			<ymin>10</ymin>
			<xmax>79</xmax>
			<ymax>63</ymax>
		</bndbox>
	</object>
	<object>
		<name>e</name>
		<pose>Unspecified</pose>
		<truncated>0</truncated>
		<difficult>0</difficult>
		<bndbox>
			<xmin>87</xmin>
			<ymin>22</ymin>
			<xmax>118</xmax>
			<ymax>61</ymax>
		</bndbox>
	</object>
	<object>
		<name>g</name>
		<pose>Unspecified</pose>
		<truncated>0</truncated>
		<difficult>0</difficult>
		<bndbox>
			<xmin>126</xmin>
			<ymin>19</ymin>
			<xmax>162</xmax>
			<ymax>65</ymax>
		</bndbox>
	</object>
	<object>
		<name>b</name>
		<pose>Unspecified</pose>
		<truncated>0</truncated>
		<difficult>0</difficult>
		<bndbox>
			<xmin>171</xmin>
			<ymin>16</ymin>
			<xmax>203</xmax>
			<ymax>63</ymax>
		</bndbox>
	</object>
</annotation>
